CHANGELOG
LICENSE
MANIFEST.in
README.rst
setup.py
django_sorl_hacks.egg-info/PKG-INFO
django_sorl_hacks.egg-info/SOURCES.txt
django_sorl_hacks.egg-info/dependency_links.txt
django_sorl_hacks.egg-info/requires.txt
django_sorl_hacks.egg-info/top_level.txt
sorl_hacks/__init__.py
sorl_hacks/admin.py
sorl_hacks/models.py
sorl_hacks/utils.py
sorl_hacks/views.py
sorl_hacks/management/__init__.py
sorl_hacks/management/commands/__init__.py
sorl_hacks/management/commands/thumbsforapp.py
sorl_hacks/templatetags/__init__.py
sorl_hacks/templatetags/sorl_hacks.py