Metadata-Version: 1.1
Name: django-sorl-hacks
Version: 0.1
Summary: Some usefull hacks based on sorl-thumbnail
Home-page: https://github.com/zerc/sorl_hacks
Author: Vladimir Savin
Author-email: zero13cool@yandex.ru
License: MIT
Platform: UNKNOWN
Classifier: Development Status :: 3 - Alpha
Classifier: License :: OSI Approved :: MIT License
Classifier: Operating System :: OS Independent
Classifier: Programming Language :: Python
Classifier: Framework :: Django
Classifier: Environment :: Web Environment
Classifier: Intended Audience :: Developers
Classifier: Topic :: Internet :: WWW/HTTP
Classifier: Topic :: Software Development :: Libraries :: Python Modules
